cicada/__init__.py
cicada/cli.py
cicada/commands/__init__.py
cicada/commands/archive_schedule_log.py
cicada/commands/delete_schedule.py
cicada/commands/exec_schedule.py
cicada/commands/exec_server_schedules.py
cicada/commands/list_schedules.py
cicada/commands/list_server_schedules.py
cicada/commands/ping_slack.py
cicada/commands/register_server.py
cicada/commands/show_schedule.py
cicada/commands/spread_schedules.py
cicada/commands/upsert_schedule.py
cicada/lib/__init__.py
cicada/lib/postgres.py
cicada/lib/scheduler.py
cicada/lib/utils.py
cicada-0.9.0.dist-info/licenses/LICENSE
cicada-0.9.0.dist-info/METADATA
cicada-0.9.0.dist-info/WHEEL
cicada-0.9.0.dist-info/entry_points.txt
cicada-0.9.0.dist-info/top_level.txt
cicada-0.9.0.dist-info/RECORD
