Metadata-Version: 2.4
Name: cicada
Version: 0.9.0
Summary: Lightweight, agent-based, distributed scheduler
Home-page: https://github.com/transferwise/cicada
Author: Wise
Classifier: License :: OSI Approved :: Apache Software License
Classifier: Programming Language :: Python :: 3 :: Only
License-File: LICENSE
Requires-Dist: psycopg2-binary==2.9.*
Requires-Dist: pyyaml==6.0.*
Requires-Dist: croniter<3.1,>=2.0
Requires-Dist: tabulate==0.9.*
Requires-Dist: slack-sdk==3.37.*
Requires-Dist: backoff==2.2.*
Provides-Extra: dev
Requires-Dist: pytest==8.2.*; extra == "dev"
Requires-Dist: pytest-cov==5.0.*; extra == "dev"
Requires-Dist: pytest-mock==3.14.*; extra == "dev"
Requires-Dist: black==24.4.*; extra == "dev"
Requires-Dist: flake8==7.1.*; extra == "dev"
Requires-Dist: freezegun==1.5.*; extra == "dev"
Dynamic: author
Dynamic: classifier
Dynamic: description
Dynamic: description-content-type
Dynamic: home-page
Dynamic: license-file
Dynamic: provides-extra
Dynamic: requires-dist
Dynamic: summary
